MzEnigma/__init__.py
MzEnigma/analyzeEnigma.py
MzEnigma/component.py
MzEnigma/enigma.py
MzEnigma/readme.rst
MzEnigma/Resources/2WH.txt
MzEnigma/Resources/3WH.txt
MzEnigma/Resources/book.txt
MzEnigma/Resources/english_bigrams.txt
MzEnigma/Resources/english_logbigrams.txt
MzEnigma/Resources/english_logtrigrams.txt
MzEnigma/Resources/english_monograms.txt
MzEnigma/Resources/english_trigrams.txt
MzEnigma/Resources/enigma_logbigrams.txt
MzEnigma/Resources/enigma_logtrigrams.txt
MzEnigma/Resources/faust.txt
MzEnigma/Resources/french_bigrams.txt
MzEnigma/Resources/french_monograms.txt
MzEnigma/Resources/frenchbook.txt
MzEnigma/Resources/german1941_bigrams.txt
MzEnigma/Resources/german1941_trigrams.txt
MzEnigma/Resources/german_bigrams.txt
MzEnigma/Resources/german_logbigrams.txt
MzEnigma/Resources/german_logtrigrams.txt
MzEnigma/Resources/german_monograms.txt
MzEnigma/Resources/germanbook.txt
MzEnigma-1.1.2.dist-info/METADATA
MzEnigma-1.1.2.dist-info/WHEEL
MzEnigma-1.1.2.dist-info/license.gpl3
MzEnigma-1.1.2.dist-info/top_level.txt
MzEnigma-1.1.2.dist-info/RECORD
