Metadata-Version: 2.1
Name: MzEnigma
Version: 1.1.2
Summary: A Simulator for Enigma operation and analysis
Home-page: https://github.com/ReinhardM-dev/MzEnigma
Author: Reinhard Maerz
License: UNKNOWN
Project-URL: Documentation, https://reinhardm-dev.github.io/MzEnigma
Platform: UNKNOWN
Classifier: Programming Language :: Python
Classifier: License :: OSI Approved :: GNU General Public License v3 or later (GPLv3+)
Classifier: Operating System :: OS Independent
Classifier: Programming Language :: Python :: 3 :: Only
Classifier: Development Status :: 4 - Beta
Classifier: Natural Language :: English
Classifier: Topic :: Security :: Cryptography
Requires-Python: >=3.7
License-File: license.gpl3
Requires-Dist: networkx (>=2.5)
